amonite/__init__.py
amonite/animation.py
amonite/benchmark.py
amonite/camera.py
amonite/controllers.py
amonite/cursor_input_handler.py
amonite/dialog_node.py
amonite/door_node.py
amonite/fall_node.py
amonite/input_controller.py
amonite/interaction_controller.py
amonite/interaction_node.py
amonite/inventory_controller.py
amonite/loading_indicator_node.py
amonite/map_cursor_node.py
amonite/node.py
amonite/scene_node.py
amonite/settings.py
amonite/shaded_sprite.py
amonite/shaders_utils.py
amonite/sound_controller.py
amonite/sprite_node.py
amonite/state_machine.py
amonite/stats.py
amonite/text_node.py
amonite/tilemap_node.py
amonite/upscaler.py
amonite/wall_node.py
amonite/collision/collision_controller.py
amonite/collision/collision_node.py
amonite/collision/collision_shape.py
amonite/dungen/dungen.py
amonite/dungen/room.py
amonite/menu/menu_node.py
amonite/shapes/circle_node.py
amonite/shapes/line_node.py
amonite/shapes/rect_node.py
amonite/shapes/shape_node.py
amonite/utils/hittables_loader.py
amonite/utils/tween.py
amonite/utils/types.py
amonite/utils/utils.py
amonite/utils/walls_loader.py
amonite-0.2.9.dist-info/METADATA
amonite-0.2.9.dist-info/WHEEL
amonite-0.2.9.dist-info/licenses/LICENSE
amonite-0.2.9.dist-info/RECORD
