Metadata-Version: 2.4
Name: amonite
Version: 0.2.9
Summary: A basic game engine built around pyglet
Project-URL: Homepage, https://github.com/Mathorga/amonite
Project-URL: Issues, https://github.com/Mathorga/amonite/issues
Project-URL: Source, https://github.com/Mathorga/amonite
Project-URL: Changelog, https://github.com/Mathorga/amonite/blob/master/CHANGELOG.md
Author-email: Luka Micheletti <michelettiluka@gmail.com>
License-File: LICENSE
Classifier: License :: OSI Approved :: MIT License
Classifier: Operating System :: OS Independent
Classifier: Programming Language :: Python :: 3
Requires-Python: >=3.12
